divide21env/__init__.py
divide21env/envs/__init__.py
divide21env/envs/divide21_env.py
divide21env/inspection/__init__.py
divide21env/inspection/inspector.py
divide21env/utils/__init__.py
divide21env/utils/logger.py
divide21env-0.2.7.dist-info/licenses/LICENSE
divide21env-0.2.7.dist-info/METADATA
divide21env-0.2.7.dist-info/WHEEL
divide21env-0.2.7.dist-info/top_level.txt
divide21env-0.2.7.dist-info/RECORD
