Metadata-Version: 2.4
Name: divide21env
Version: 0.2.7
Summary: Gymnasium environment for the game Divide21
Home-page: https://github.com/jaci-hub/divide21Env
Author: Jacinto Jeje Matamba Quimua
License: MIT
Project-URL: Source, https://github.com/jaci-hub/divide21Env
Requires-Python: >=3.11
License-File: LICENSE
Requires-Dist: gymnasium>=0.30.0
Requires-Dist: numpy>=1.23
Dynamic: home-page
Dynamic: license-file
Dynamic: requires-python
